MANIFEST.in
README.md
requirements-dev.txt
requirements.txt
setup.cfg
setup.py
chaostoolkit_process_logger.egg-info/PKG-INFO
chaostoolkit_process_logger.egg-info/SOURCES.txt
chaostoolkit_process_logger.egg-info/dependency_links.txt
chaostoolkit_process_logger.egg-info/requires.txt
chaostoolkit_process_logger.egg-info/top_level.txt
process_logger/__init__.py
process_logger/actions.py
process_logger/probes.py