Metadata-Version: 1.2
Name: chaostoolkit-process-logger
Version: 0.1.4
Summary: Chaos Toolkit Extension that logs the process output
Home-page: https://github.com/opentable/chaostoolkit-process-logger.git
Author: Hung Tran
Author-email: contact@chaostoolkit.org
License: Apache License Version 2.0
Keywords: chaostoolkit,logger,process logger
Platform: UNKNOWN
Classifier: Development Status :: 2 - Pre-Alpha
Classifier: Intended Audience :: Developers
Classifier: License :: Freely Distributable
Classifier: Operating System :: OS Independent
Classifier: License :: OSI Approved :: Apache Software License
Classifier: Programming Language :: Python
Classifier: Programming Language :: Python :: 3
Classifier: Programming Language :: Python :: 3.5
Classifier: Programming Language :: Python :: 3.6
Classifier: Programming Language :: Python :: Implementation
Classifier: Programming Language :: Python :: Implementation :: CPython
Requires-Python: >=3.5.*
